finder/AuxiliaryFunctions.py
finder/DbscanLoop.py
finder/SimilarityScore.py
finder/__init__.py
finder/algorithm.py
finder_smlm-0.0.4.dist-info/LICENSE
finder_smlm-0.0.4.dist-info/METADATA
finder_smlm-0.0.4.dist-info/WHEEL
finder_smlm-0.0.4.dist-info/top_level.txt
finder_smlm-0.0.4.dist-info/RECORD
