Metadata-Version: 2.1
Name: finder-smlm
Version: 0.0.4
Summary: FINDER algorithm for SMLM
Author: Andreas Nold, Pietro Verzelli
License: MIT License
Classifier: License :: OSI Approved :: MIT License
Classifier: Programming Language :: Python
Classifier: Programming Language :: Python :: 3
Requires-Python: >=3.8
License-File: LICENSE
Requires-Dist: matplotlib (>=3.5.2)
Requires-Dist: numpy (>=1.22.3)
Requires-Dist: pandas (>=1.2.5)
Requires-Dist: seaborn (>=0.11.0)
Requires-Dist: scikit-learn (>=1.0.2)
